AUTHORS.rst
LICENSE
MANIFEST.in
README.md
setup.cfg
setup.py
django_saml2_auth_signout_slo/__init__.py
django_saml2_auth_signout_slo/apps.py
django_saml2_auth_signout_slo/plugins.py
django_saml2_auth_signout_slo.egg-info/PKG-INFO
django_saml2_auth_signout_slo.egg-info/SOURCES.txt
django_saml2_auth_signout_slo.egg-info/dependency_links.txt
django_saml2_auth_signout_slo.egg-info/requires.txt
django_saml2_auth_signout_slo.egg-info/top_level.txt